polyominator/__init__.py
polyominator/solver.py
polyominator-1.0.1.dist-info/LICENSE
polyominator-1.0.1.dist-info/METADATA
polyominator-1.0.1.dist-info/WHEEL
polyominator-1.0.1.dist-info/top_level.txt
polyominator-1.0.1.dist-info/RECORD
