Metadata-Version: 2.2
Name: polyominator
Version: 1.0.1
Summary: Polyomino task solver.
Home-page: https://github.com/KirilinAM/Polyomino-solver
Author: Artem
Author-email: kirilinartem@yandex.ru
License-File: LICENSE
Requires-Dist: algorithm-x
Requires-Dist: numpy
Requires-Dist: pandas
Requires-Dist: python-dateutil
Requires-Dist: pytz
Requires-Dist: scipy
Requires-Dist: six
Requires-Dist: tzdata
Dynamic: author
Dynamic: author-email
Dynamic: description
Dynamic: description-content-type
Dynamic: home-page
Dynamic: requires-dist
Dynamic: summary
